jirafs_plantuml/__init__.py
jirafs_plantuml/plugin.py
jirafs_plantuml-1.0.0.dist-info/METADATA
jirafs_plantuml-1.0.0.dist-info/WHEEL
jirafs_plantuml-1.0.0.dist-info/entry_points.txt
jirafs_plantuml-1.0.0.dist-info/top_level.txt
jirafs_plantuml-1.0.0.dist-info/RECORD
