Metadata-Version: 2.1
Name: jirafs-plantuml
Version: 1.0.0
Summary: Automatically convert plantuml diagrams into images without ever leaving your editor.
Home-page: https://github.com/coddingtonbear/jirafs-plantuml
Author: Adam Coddington
Author-email: me@adamcoddington.net
License: UNKNOWN
Platform: UNKNOWN
Classifier: License :: OSI Approved :: MIT License
Classifier: Operating System :: OS Independent
Classifier: Programming Language :: Python :: 3
Requires-Dist: six
